escformatter/__init__.py
escformatter/esc.py
escformatter-0.1.1.3.dist-info/LICENSE
escformatter-0.1.1.3.dist-info/METADATA
escformatter-0.1.1.3.dist-info/WHEEL
escformatter-0.1.1.3.dist-info/top_level.txt
escformatter-0.1.1.3.dist-info/RECORD
