Metadata-Version: 2.1
Name: escformatter
Version: 0.1.1.3
Summary: A Python class for executing ANSI escape commands in the console.
Home-page: https://github.com/devleonardoamaral/escformatter.git
Author: Leonardo S. Amaral
Author-email: leonardo_amaral98@hotmail.com
Classifier: Programming Language :: Python :: 3
Classifier: License :: OSI Approved :: MIT License
Classifier: Operating System :: OS Independent
Requires-Python: >=3.7
License-File: LICENSE
